jaycopilot_client/__init__.py
jaycopilot_client/client.py
jaycopilot_client/config.py
jaycopilot_client/exception/client_exception.py
jaycopilot_client/schemas.py
jaycopilot_client-0.2.0.dist-info/METADATA
jaycopilot_client-0.2.0.dist-info/WHEEL
jaycopilot_client-0.2.0.dist-info/RECORD
